isdn_ld/__init__.py
isdn_ld/command.py
isdn_ld/mappers/__init__.py
isdn_ld/mappers/isdn.py
isdn_ld/namespace.py
isdn_ld-0.1.0.dist-info/METADATA
isdn_ld-0.1.0.dist-info/WHEEL
isdn_ld-0.1.0.dist-info/entry_points.txt
isdn_ld-0.1.0.dist-info/licenses/LICENSE
isdn_ld-0.1.0.dist-info/RECORD
