Metadata-Version: 2.4
Name: isdn-ld
Version: 0.1.0
Summary: A tool to generate the Linked Data dataset for ISDN
License: MIT
License-File: LICENSE
Keywords: rdf,linked data
Author: Babibubebon
Author-email: babibubebon@babibubebo.org
Requires-Python: >=3.12,<4.0
Classifier: License :: OSI Approved :: MIT License
Classifier: Programming Language :: Python :: 3
Classifier: Programming Language :: Python :: 3.12
Classifier: Programming Language :: Python :: 3.13
Classifier: Programming Language :: Python :: 3.14
Requires-Dist: click (>=8.3.1,<9.0.0)
Requires-Dist: isal (>=1.8.0,<2.0.0)
Requires-Dist: isdn (>=2.0.0,<3.0.0)
Requires-Dist: joblib (>=1.5.3,<2.0.0)
Requires-Dist: rdflib (>=7.5.0,<8.0.0)
Project-URL: Homepage, https://github.com/Babibubebon/isdn-ld
Project-URL: Repository, https://github.com/Babibubebon/isdn-ld
